{
  "appInfo" : {
    "build" : "232.10227.11",
    "buildDate" : "2023-11-13T23:43:44.199Z[UTC]",
    "productCode" : "PC",
    "generated" : "2023-12-26T17:20:57.300852619Z",
    "os" : "Linux 5.15.0-91-generic",
    "runtime" : "JetBrains s.r.o. 17.0.9 17.0.9+7-b1000.46"
  },
  "runtimeInfo" : {
    "maxMemory" : 2147483648,
    "numberOfProcessors" : 4,
    "maxNumberOfIndexingThreads" : 3,
    "maxSizeOfFileForIntelliSense" : 2560000,
    "maxSizeOfFileForContentLoading" : 20971520
  },
  "type" : "Scanning",
  "projectIndexingActivityHistory" : {
    "projectName" : "WeatherEnglish",
    "times" : {
      "scanningReason" : "On project open",
      "scanningType" : "FULL_ON_PROJECT_OPEN",
      "scanningId" : 1,
      "creatingIteratorsTime" : 1882273,
      "collectingIndexableFilesTime" : 3619143524,
      "delayedPushPropertiesStageTime" : 3248789,
      "indexExtensionsTime" : 0,
      "dumbWallTimeWithPauses" : 0,
      "dumbWallTimeWithoutPauses" : 0,
      "updatingStart" : "2023-12-26T17:20:53.633195276Z",
      "updatingEnd" : "2023-12-26T17:20:57.289720642Z",
      "totalWallTimeWithPauses" : 3656534088,
      "wallTimeOnPause" : 0,
      "wasInterrupted" : false,
      "totalWallTimeWithoutPauses" : 3656534088
    },
    "fileCount" : {
      "numberOfFileProviders" : 6,
      "numberOfScannedFiles" : 6104,
      "numberOfFilesIndexedByInfrastructureExtensionsDuringScan" : 0,
      "numberOfFilesScheduledForIndexingAfterScan" : 0
    },
    "scanningStatistics" : [ {
      "providerName" : "Python SDK Python 3.10 (WeatherEnglish) /home/kadosh/PycharmProjects/WeatherEnglish/venv/bin/python",
      "numberOfScannedFiles" : 5875,
      "numberOfSkippedFiles" : 1,
      "numberOfFilesForIndexing" : 0,
      "numberOfFilesFullyIndexedByInfrastructureExtensions" : 0,
      "filesFullyIndexedByInfrastructureExtensions" : [ ],
      "statusTime" : 2516540200,
      "scanningTime" : 2610836322,
      "timeProcessingUpToDateFiles" : 848966772,
      "timeUpdatingContentLessIndexes" : 19415841,
      "timeIndexingWithoutContentViaInfrastructureExtension" : 0,
      "roots" : [ ]
    }, {
      "providerName" : "Indexable set contributor 'com.intellij.javaee.ExternalResourcesRootsProvider@2486d0f8' (non-project)",
      "numberOfScannedFiles" : 209,
      "numberOfSkippedFiles" : 4,
      "numberOfFilesForIndexing" : 0,
      "numberOfFilesFullyIndexedByInfrastructureExtensions" : 0,
      "filesFullyIndexedByInfrastructureExtensions" : [ ],
      "statusTime" : 113870661,
      "scanningTime" : 117864099,
      "timeProcessingUpToDateFiles" : 30519122,
      "timeUpdatingContentLessIndexes" : 552057,
      "timeIndexingWithoutContentViaInfrastructureExtension" : 0,
      "roots" : [ ]
    }, {
      "providerName" : "Module 'WeatherEnglish' (all roots)",
      "numberOfScannedFiles" : 20,
      "numberOfSkippedFiles" : 0,
      "numberOfFilesForIndexing" : 0,
      "numberOfFilesFullyIndexedByInfrastructureExtensions" : 0,
      "filesFullyIndexedByInfrastructureExtensions" : [ ],
      "statusTime" : 102498997,
      "scanningTime" : 109603351,
      "timeProcessingUpToDateFiles" : 77124396,
      "timeUpdatingContentLessIndexes" : 5335404,
      "timeIndexingWithoutContentViaInfrastructureExtension" : 0,
      "roots" : [ ]
    }, {
      "providerName" : "Indexable set contributor 'Scratches & Consoles' (project)",
      "numberOfScannedFiles" : 0,
      "numberOfSkippedFiles" : 0,
      "numberOfFilesForIndexing" : 0,
      "numberOfFilesFullyIndexedByInfrastructureExtensions" : 0,
      "filesFullyIndexedByInfrastructureExtensions" : [ ],
      "statusTime" : 0,
      "scanningTime" : 0,
      "timeProcessingUpToDateFiles" : 0,
      "timeUpdatingContentLessIndexes" : 0,
      "timeIndexingWithoutContentViaInfrastructureExtension" : 0,
      "roots" : [ ]
    }, {
      "providerName" : "Indexable set contributor 'Scratches & Consoles' (non-project)",
      "numberOfScannedFiles" : 0,
      "numberOfSkippedFiles" : 0,
      "numberOfFilesForIndexing" : 0,
      "numberOfFilesFullyIndexedByInfrastructureExtensions" : 0,
      "filesFullyIndexedByInfrastructureExtensions" : [ ],
      "statusTime" : 0,
      "scanningTime" : 0,
      "timeProcessingUpToDateFiles" : 0,
      "timeUpdatingContentLessIndexes" : 0,
      "timeIndexingWithoutContentViaInfrastructureExtension" : 0,
      "roots" : [ ]
    }, {
      "providerName" : "Indexable set contributor 'com.intellij.javaee.ExternalResourcesRootsProvider@2486d0f8' (project)",
      "numberOfScannedFiles" : 0,
      "numberOfSkippedFiles" : 0,
      "numberOfFilesForIndexing" : 0,
      "numberOfFilesFullyIndexedByInfrastructureExtensions" : 0,
      "filesFullyIndexedByInfrastructureExtensions" : [ ],
      "statusTime" : 0,
      "scanningTime" : 0,
      "timeProcessingUpToDateFiles" : 0,
      "timeUpdatingContentLessIndexes" : 0,
      "timeIndexingWithoutContentViaInfrastructureExtension" : 0,
      "roots" : [ ]
    } ]
  }
}